{
    "name": {
        "en": "Black-Back Perch Stew",
        "de": "Gekochter Schwarzrückenbarsch",
        "chs": "水煮黑背鲈",
        "cht": "水煮黑背鱸",
        "es": "Estofado de perca de lomo negro",
        "fr": "Marmite de perche à dos noir",
        "id": "Black-Back Perch Stew",
        "jp": "黒背スズキの唐辛子煮込み",
        "kr": "삶은 검정 농어",
        "pt": "Ensopado de Poleiro com Dorso Negro",
        "ru": "Чёрный окунь",
        "th": "Black-Back Perch Stew",
        "vi": "Cá Chép Đen Hấp"
    },
    "id": 3102,
    "foodType": "COOK_FOOD_HEAL",
    "cookMethod": "COOK_METHOD_BOIL",
    "rankLevel": 3,
    "isDefaultUnlocked": false,
    "maxProficiency": 15,
    "inputVec": [
        {
            "id": 100084,
            "count": 3
        },
        {
            "id": 100027,
            "count": 1
        },
        {
            "id": 100075,
            "count": 1
        },
        {
            "id": 100034,
            "count": 1
        },
        {}
    ],
    "qualityOutputVec": [
        {
            "id": 108074,
            "count": 1
        },
        {
            "id": 108075,
            "count": 1
        },
        {
            "id": 108076,
            "count": 1
        }
    ],
    "qteParam": "0.4,0.27",
    "qteQualityWeightVec": [
        0,
        0,
        100
    ],
    "effectDesc": {
        "en": "Restores <color=#3399CCFF>26–30%</color> of Max HP to the selected character. Regenerates <color=#3399CCFF>450–790</color> HP every 5s for the next 30s.",
        "de": "Stellt der gewählten Figur <color=#3399CCFF>26 bis 30 %</color> LP wieder her. Stellt innerhalb der nächsten 30 s alle 5 s <color=#3399CCFF>450 bis 790</color> LP wieder her.",
        "chs": "为选中的角色恢复生命值上限的<color=#3399CCFF>26%-30%</color>。 并在之后的30秒内，每5秒恢复<color=#3399CCFF>450-790</color>点生命值。",
        "cht": "為選中的角色恢復生命值上限的<color=#3399CCFF>26%-30%</color>。 並在之後的30秒內，每5秒恢復<color=#3399CCFF>450-790</color>點生命值。",
        "es": "Restaura un <color=#3399CCFF>26%-30%</color> de Vida Máx. al personaje seleccionado. Regenera <color=#3399CCFF>450-790</color> pts. de Vida cada 5 s durante 30 s.",
        "fr": "Restaure <color=#3399CCFF>26 à 30 %</color> des PV max du personnage sélectionné. Et restaure <color=#3399CCFF>450 à 790</color> PV toutes les 5 s pendant 30 s.",
        "id": "Memulihkan <color=#3399CCFF>26–30%</color> HP Karakter yang dipilih. Memberikan regenerasi <color=#3399CCFF>450–790</color> HP setiap 5 detik selama 30 detik.",
        "jp": "選択したキャラのHP上限の<color=#3399CCFF>26%~30%</color>を回復する。 その後30秒間、5秒毎にHPを<color=#3399CCFF>450~790</color>回復する。",
        "kr": "선택한 캐릭터 HP 최대치의 <color=#3399CCFF>26%-30%</color>를 회복한다 이후 30초 동안 5초마다 HP를 <color=#3399CCFF>450-790</color>pt씩 회복한다",
        "pt": "Restaura <color=#3399CCFF>26% - 30%</color> da Vida Máxima ao personagem selecionado. Regenera <color=#3399CCFF>450 - 790</color> de Vida a cada 5s por 30s.",
        "ru": "Восстанавливает выбранному персонажу <color=#3399CCFF>26%-30%</color> от макс. HP. Восстанавливает <color=#3399CCFF>450-790</color> HP каждые 5 сек. в течение 30 сек.",
        "th": "ฟื้นฟูพลังชีวิตให้ตัวละครที่เลือก <color=#3399CCFF>26%-30%</color> และภายใน 30 วินาที หลังจากนั้น จะทำการฟื้นฟูพลังชีวิต <color=#3399CCFF>450-790</color> หน่วย ในทุก 5 วินาที",
        "vi": "Hồi <color=#3399CCFF>26%-30%</color> giới hạn HP cho nhân vật được chọn. Trong 30s tiếp theo, mỗi 5s hồi <color=#3399CCFF>450-790</color> HP."
    }
}