{
    "name": {
        "en": "Fertile Soil (Reportedly)",
        "de": "Angeblich sehr fruchtbarer Lehm",
        "chs": "据说很肥沃的泥土",
        "cht": "據說很肥沃的泥土",
        "es": "Barro aparentemente muy fértil",
        "fr": "Terre supposément fertile",
        "id": "Konon Katanya Tanah Gembur",
        "jp": "肥沃な土？",
        "kr": "비옥하다는 소문이 도는 진흙",
        "pt": "Barro Aparentemente Fértil",
        "ru": "Якобы плодородная земля",
        "th": "ดินที่ว่ากันว่าอุดมสมบูรณ์มาก",
        "vi": "Bùn Đất Nghe Nói Rất Màu Mỡ"
    },
    "id": 101914,
    "materialDesc": {
        "en": "You can't tell whether this soil is fertile or not.\\nWhat will Akim use this for?",
        "de": "Lehm, dem man nicht ansieht, ob er besonders fruchtbar ist oder nicht.\\nWozu Akim den wohl benutzen möchte?",
        "chs": "看不出来肥沃与否的泥土。\\n不知道阿金会拿来做什么…",
        "cht": "看不出來肥沃與否的泥土。\\n不知道阿金會拿來做什麼…",
        "es": "Barro de supuesta gran fertilidad. ¿Para qué lo querrá Akim?",
        "fr": "#Il est difficile de dire si cette terre est fertile ou non.\\nÀ quoi ce truc va-t-il servir à Akim{NON_BREAK_SPACE}?",
        "id": "Kamu bahkan tidak yakin apakah tanah ini gembur atau tidak.\\nAkim mau pakai buat apa sih?",
        "jp": "肥沃かどうか、判断がつかない土。\\nアキムはこれを何に使うんだろう…",
        "kr": "비옥한지 아닌지 알 수 없는 진흙.\\n아킴은 이걸로 뭘 하려는 걸까…",
        "pt": "Não dá para saber se esse solo é fértil ou não.\\nMe pergunto por que o Akim quer um desses?",
        "ru": "Внешне не отличается от самой обычной земли.\\nИнтересно, зачем она понадобилась Акиму...",
        "th": "ดินที่ดูไม่ออกว่าอุดมสมบูรณ์จริงหรือเปล่า\\nไม่รู้ว่า Akim จะเอามาทำอะไรกันแน่...",
        "vi": "Loại đất nhìn vào không thể biết có màu mỡ hay không.\\nKhông biết Akim dùng nó để làm gì..."
    },
    "materialType": "MATERIAL_QUEST"
}