{
    "name": {
        "en": "Flaming Red Bolognese",
        "de": "Feurige Nudeln",
        "chs": "火火肉酱面",
        "cht": "火火肉醬麵",
        "es": "Pasta a la boloñesa",
        "fr": "Pâtes à la bolognaise enflammées",
        "id": "Flaming Red Bolognese",
        "jp": "完熟トマトのミートソース",
        "kr": "불꽃 미트 스파게티",
        "pt": "Macarrão à Bolonhesa Picante",
        "ru": "Паста с томатным соусом",
        "th": "Flaming Red Bolognese",
        "vi": "Mỳ Sốt Thịt"
    },
    "id": 108016,
    "materialDesc": {
        "en": "Bolognese covered with a meat sauce. The meaty, herby aroma really gets your appetite going.",
        "de": "Spaghetti mit richtig viel Soße. Die Tomatensoße ist von feurigem Rot und wird begleitet von einer leicht säuerlich-süßen Note.",
        "chs": "淋满肉酱的细面。细面被番茄酱着上红红火火的色彩，酸甜可口，非常开胃。",
        "cht": "淋滿肉醬的細麵。細麵被番茄醬染上紅紅火火的色彩，酸甜可口，非常開胃。",
        "es": "Pasta con mucha salsa boloñesa. El aroma a carne y hierbas abre el apetito.",
        "fr": "Pâtes nappées d'une sauce à la viande. Leur apparence et leur goût aigre-doux ouvrent l'appétit.",
        "id": "Bolognese yang penuh dengan saus daging. Aroma gabungan daging dan herba yang harum mudah membuat air liurmu mengalir.",
        "jp": "ミートソースたっぷりのスパゲッティ。スパゲッティがトマトソースで真っ赤に彩られている。甘酸っぱく美味しく、食欲をかきたてる。",
        "kr": "다진 고기가 듬뿍 들어간 스파게티. 토마토 소스와 어우러져 먹음직스럽게 보인다. 새콤달콤해 식욕을 돋운다",
        "pt": "Macarrão à Bolonhesa. O aroma da carne e das ervas só aumentam o apetite.",
        "ru": "Паста, покрытая томатным соусом с фаршем. Аромат свежих томатов не на шутку возбуждает аппетит.",
        "th": "เมนูสปาเก็ตตี้อันแสนโอชะที่ราดด้วยซอสเนื้อหอมกรุ่น ตัวเส้นที่สไลด์บาง ๆ คลุกด้วยซอสมะเขือเทศสีแดงสดราวกับเปลวเพลิงซึ่งให้รสหวานอมเปรี้ยว เป็นเมนูที่จะทำให้ความอยากอาหารในตัวของคุณนั้นตื่นขึ้นมาอย่างไม่สิ้นสุด",
        "vi": "Sợi mì thấm đầy nước thịt. Sốt cà chua khiến sợi mì trông đỏ tươi, chua ngọt vừa miệng."
    },
    "materialType": "MATERIAL_NOTICE_ADD_HP"
}