{
    "name": {
        "en": "Recipe: Mint Salad",
        "de": "Rezept: Minzsalat",
        "chs": "食谱：凉拌薄荷",
        "cht": "食譜：涼拌薄荷",
        "es": "Receta: Ensalada de menta",
        "fr": "Recette : Salade de menthe froide",
        "id": "Resep: Mint Salad",
        "jp": "レシピ：ミントの和え物",
        "kr": "레시피: 허브냉채",
        "pt": "Receita: Salada de Menta",
        "ru": "Рецепт: Мятный салат",
        "th": "สูตรอาหาร: Mint Salad",
        "vi": "Công thức: Rau Trộn Bạc Hà"
    },
    "id": 109446,
    "materialDesc": {
        "en": "A detailed step-by-step recipe for making Mint Salad.",
        "de": "Rezept mit detaillierten Schritten zur Zubereitung von „Minzsalat“.",
        "chs": "步骤详实的食谱，记载着「凉拌薄荷」的制作方法。",
        "cht": "步驟詳實的食譜，記載著「涼拌薄荷」的製作方法。",
        "es": "Receta paso a paso para hacer una ensalada de menta.",
        "fr": "Étapes de préparation de la salade de menthe froide.",
        "id": "Resep yang berisi langkah-langkah untuk membuat Mint Salad.",
        "jp": "「ミントの和え物」の詳しい作り方が載っているレシピ。",
        "kr": "조리 과정이 자세히 적혀 있는 레시피. 「허브냉채」의 조리 방법이 적혀있다",
        "pt": "Uma receita com o passo a passo detalhado de como fazer Salada de Menta.",
        "ru": "Подробный рецепт приготовления блюда «Мятный салат».",
        "th": "สูตรอธิบายวิธีทำ \"Mint Salad\" โดยละเอียด",
        "vi": "Công thức món ăn, ghi lại cách làm món \"Rau Trộn Bạc Hà\""
    },
    "materialType": "MATERIAL_CONSUME"
}